{"name":"synth-haskell","tagline":"MIDI to WAVE synthesizer","body":"## Installation\r\n\r\n```\r\n$ cabal install\r\n```\r\n\r\nInstalls dependencies, takes some time.\r\n*(GHC size is ~800 MB, so you wouldn't expect it to include libraries for\r\ncommand line arguments processing, regexps, unit testing etc., right?)*\r\nAlso compiles the project and creates an executable `~/.cabal/bin/synth`.\r\n\r\n## Run\r\n\r\n```\r\n$ synth input.midi [output.wav]\r\n```\r\n\r\nRuns for ages.\r\n*Since rendering functions are pure Haskell functions with fixed results based just on arguments\r\nwith no side effects whatsoever, you don't really expect GHC to cache them by any means, do you?*\r\n","google":"","note":"Don't delete this file! It's used internally to help with page regeneration."}